mcp_hmr-0.0.3.2.dist-info/METADATA
mcp_hmr-0.0.3.2.dist-info/WHEEL
mcp_hmr-0.0.3.2.dist-info/entry_points.txt
mcp_hmr.py
mcp_hmr-0.0.3.2.dist-info/RECORD
