Metadata-Version: 2.1
Name: mcp-hmr
Version: 0.0.3.2
Summary: Hot Reloading for MCP Servers
Keywords: mcp,hot-reload,hmr,reload,server
Author-Email: Muspi Merol <me@promplate.dev>
License: MIT
Classifier: Development Status :: 2 - Pre-Alpha
Classifier: Intended Audience :: Developers
Classifier: Operating System :: OS Independent
Project-URL: Homepage, https://github.com/promplate/hmr
Project-URL: Documentation, https://hmr.promplate.dev
Project-URL: Repository, https://github.com/promplate/hmr/tree/HEAD/packages/mcp-hmr
Requires-Python: >=3.12
Requires-Dist: fastmcp<3,>=2.2.0
Requires-Dist: hmr~=0.7.0
